Workbook

Sheet Cash Book
A1: SUPERANNUATION FUND OF THE NIGER ANGLICAN CHURCHES
A2: RECIEPT AND PAYMENT
B4: january | C4: February | D4: March | E4: April | F4: May | G4: JUNE | H4: july | I4: August | J4: september | K4: October | L4: November | M4: December
A5: BAL-Cash | B5: 641997.55 | C5: 101161 | D5: -98979 | E5: 90121 | F5: 72821 | G5: 820821 | H5: 716871 | I5: 162021 | J5: 561721 | K5: 567821 | L5: 273521 | M5: 570221 | N5: 641997.55
A6: FBN 1 | B6: 1.26986e+08 | C6: 1.82938e+08 | D6: 1.0256161e+08 | E6: 83404793 | F6: 91931664 | G6: 4654336.1 | H6: 16632405 | I6: 42031948 | J6: 57059251 | K6: 81999240 | L6: 1.0193841e+08 | M6: 47686522 | N6: 1.26986e+08
A7: FBN 2 | B7: 237180.1 | C7: 157873.31 | D7: -354340.06 | E7: 1991688.3 | F7: 1906160.5 | G7: 978760.83 | H7: 374042.73 | I7: 38295.6 | J7: 1261762.4 | K7: 2079392.6 | L7: 1301934.1 | M7: 682591.34 | N7: 237180.1
A8: Zenith Bank | B8: 1545213.4 | C8: 1545213.4 | D8: 1545213.4 | E8: 2.0614974e+08 | F8: 4.7722924e+08 | G8: 3.7226786e+08 | H8: 2.2218288e+08 | I8: 1.839948e+08 | J8: 1.6251434e+08 | K8: 1.6363426e+08 | L8: 1.1206597e+08 | M8: 1.1734248e+08 | N8: 1545213.4
A9: Contribution | B9: 74471574 | C9: 20192347 | D9: 27005082 | E9: 7060196.7 | F9: 14710679 | G9: 2139900.2 | H9: 22314809 | I9: 67994046 | J9: 32341531 | K9: 15041242 | L9: 23290128 | M9: 1.1711804e+08 | N9: =SUM(B9:M9) -> 4.2367958e+08
A10: Intrest Income | B10: 486643.15 | C10: 7889389.7 | E10: 2549933.1 | G10: 10236207 | H10: 6073111.6 | K10: 5577732.4 | L10: 5311475.4 | M10: 15131858 | N10: =SUM(B10:M10) -> 53256350
A11: Dividend | E11: 50914.98 | F11: 559.8 | G11: 352593 | H11: 4640 | K11: 143318.75 | L11: 353969.01 | N11: =SUM(B11:M11) -> 905995.54
A12: Seminer fee | B12: 2476000 | C12: 90000 | M12: 180000 | N12: =SUM(B12:M12) -> 2746000
A13: LOAN Refund | B13: 510000 | N13: =SUM(B13:M13) -> 510000
A14: ALUU Hostel rent | D14: 1604800 | E14: 1200000 | H14: 2588860 | J14: 1120000 | M14: 1878640 | N14: =SUM(B14:M14) -> 8392300
A15: Printing of Account | D15: 20000 | L15: 5000 | N15: =SUM(B15:M15) -> 25000
A16: New Card | B16: 6000 | C16: 6000 | D16: 2000 | G16: 2000 | I16: 10000 | J16: 2000 | L16: 2000 | N16: =SUM(B16:M16) -> 30000
A17: Tender | D17: 1200000 | E17: 300000 | M17: 300000 | N17: =SUM(B17:M17) -> 1800000
A18: Trianing unpaid | G18: 30000 | N18: =SUM(B18:M18) -> 30000
A19: transfer from globus | I19: 40000000 | M19: 110000000 | N19: =SUM(B19:M19) -> 150000000
A20: BGL Liquidation | K20: 1664993.4 | M20: 808711.1 | N20: =SUM(B20:M20) -> 2473704.5
A21: Staff Loan | K21: 150000 | L21: 150000 | M21: 150000 | N21: =SUM(B21:M21) -> 450000
A22: Sale of Old Battery | L22: 240000 | N22: =SUM(B22:M22) -> 240000
A23: Awka Hostel rent | L23: 4976700 | N23: =SUM(B23:M23) -> 4976700
A24: transfer from RATHbons | D24: 203000000 | E24: 370590000 | N24: =SUM(B24:M24) -> 573590000
B25: =SUM(B5:B24) -> 2.0736061e+08 | C25: =SUM(C5:C24) -> 2.1291998e+08 | D25: =SUM(D5:D24) -> 3.3648539e+08 | E25: =SUM(E5:E24) -> 6.7338739e+08 | F25: =SUM(F5:F24) -> 5.8585112e+08 | G25: =SUM(G5:G24) -> 3.9148248e+08 | H25: =SUM(H5:H24) -> 2.7088762e+08 | I25: =SUM(I5:I24) -> 3.3423111e+08 | ... N25: =SUM(N5:N24) -> 1.352516e+09
B26: =B78 -> 2.0736061e+08 | C26: 2.1291998e+08 | D26: 3.3648539e+08 | E26: 6.7338739e+08 | F26: =F78 -> 5.8585112e+08 | G26: 3.9148248e+08 | H26: 2.7088762e+08 | I26: 3.3423111e+08 | J26: 2.548606e+08 | K26: 2.70858e+08 | L26: 2.4990911e+08 | M26: =M78 -> 4.1184907e+08 | N26: =N78 -> 1.352516e+09
B27: =B25-B26 -> 0 | C27: =C25-C26 -> 0 | D27: =D25-D26 -> 0 | E27: =E25-E26 -> 0 | F27: =F25-F26 -> 0 | G27: =G25-G26 -> 0 | H27: =H25-H26 -> 0 | I27: =I25-I26 -> 0 | ... N27: =N25-N26 -> 0
H28: =H25-H26 -> 0 | N28: =SUM(B28:J28) -> 0
N29: =SUM(B29:J29) -> 0
A30: PAYMENT | N30: =SUM(B30:J30) -> 0
A31: Audit Fee | C31: 2000000 | N31: =SUM(B31:M31) -> 2000000
A32: contingency | C32: 15000 | E32: 35000 | F32: 20000 | H32: 38000 | L32: 32500 | N32: =SUM(B32:M32) -> 140500
A33: Car Running Cost | B33: 183900 | C33: 785500 | D33: 412700 | E33: 148400 | F33: 277900 | G33: 125000 | H33: 305100 | I33: 145100 | J33: 219500 | K33: 292600 | L33: 119200 | M33: 427200 | N33: =SUM(B33:M33) -> 3442100
A34: Car Insurance/Particulars Renewal | H34: 25700 | N34: =SUM(B34:M34) -> 25700
A35: Contribution Refund | C35: 7897727.3 | F35: 6915203.6 | I35: 10127727 | L35: 4206201.9 | N35: =SUM(B35:M35) -> 29146859
A36: EXCO Transport | B36: 565000 | C36: 200000 | D36: 950000 | E36: 710000 | H36: 430000 | I36: 960000 | M36: 4720000 | N36: =SUM(B36:M36) -> 8535000
A37: Equipment | F37: 310000 | K37: 1256000 | L37: 155000 | N37: =SUM(B37:M37) -> 1721000
A38: Furniture/Fittings | N38: =SUM(B38:M38) -> 0
A39: Furniture/Fittings - Awka | N39: =SUM(B39:M39) -> 0
A40: Furniture/Fittings - Aluu Hostel | C40: 17386100 | D40: 1000000 | N40: =SUM(B40:M40) -> 18386100
A41: General Transport | B41: 7800 | C41: 3750 | D41: 11600 | E41: 3700 | F41: 15400 | G41: 15700 | H41: 13450 | I41: 9600 | J41: 1000 | K41: 58200 | L41: 26300 | M41: 23750 | N41: =SUM(B41:M41) -> 190250
A42: GARC Expenses/ARM Interest | N42: =SUM(B42:M42) -> 0
A43: Hospitality | C43: 140000 | D43: 60600 | E43: 52100 | F43: 77000 | H43: 99000 | I43: 80800 | L43: 6500 | M43: 141200 | N43: =SUM(B43:M43) -> 657200
A44: Newspappers | N44: =SUM(B44:M44) -> 0
A45: foundation laying | F45: 480000 | G45: 100000 | N45: =SUM(B45:M45) -> 580000
A46: Land | F46: 450000 | N46: =SUM(B46:M46) -> 450000
A47: Land Aluu Hostel | J47: 1000000 | N47: =SUM(B47:M47) -> 1000000
A48: Land and Building- Awka | N48: =SUM(B48:M48) -> 0
A49: Aluu Hostel Expenses | G49: 180000 | I49: 200000 | L49: 290000 | N49: =SUM(B49:M49) -> 670000
A50: Light/Power | B50: 68000 | C50: 12000 | D50: 15000 | F50: 77700 | G50: 16000 | H50: 15000 | I50: 9000 | J50: 32000 | K50: 42000 | L50: 15000 | M50: 161000 | N50: =SUM(B50:M50) -> 462700
A51: Leave Allowance | J51: 105188 | K51: 78864 | L51: 123864.04 | M51: 110390 | N51: =SUM(B51:M51) -> 418306.04
A52: Newspappers | B52: 3000 | D52: 3500 | L52: 4500 | M52: 3500 | N52: =SUM(B52:M52) -> 14500
A53: Office Entertainment | B53: 25350 | C53: 24290 | D53: 28100 | E53: 20600 | F53: 10400 | H53: 13000 | I53: 21800 | J53: 6100 | K53: 32200 | L53: 11600 | M53: 19700 | N53: =SUM(B53:M53) -> 213140
A54: Pensions Paid | C54: 79703032 | F54: 76359084 | I54: 79684932 | L54: 76292245 | N54: =SUM(B54:M54) -> 3.1203929e+08
A55: Postage | B55: 6000 | C55: 18000 | D55: 64300 | E55: 3500 | F55: 7000 | G55: 7000 | H55: 3500 | I55: 7000 | J55: 3500 | K55: 7000 | L55: 3500 | M55: 5500 | N55: =SUM(B55:M55) -> 135800
A56: Repairs | B56: 110500 | C56: 86500 | E56: 17000 | F56: 100500 | G56: 31000 | H56: 6000 | K56: 12500 | L56: 61500 | N56: =SUM(B56:M56) -> 425500
A57: Salaries/Allowances | B57: 779462.11 | C57: 779462.11 | D57: 779462.11 | E57: 779462.11 | F57: 779462.11 | G57: 779462.11 | H57: 779462.11 | I57: 779462.11 | J57: 779462.11 | K57: 779462.11 | L57: 779462.11 | M57: 779462.15 | N57: =SUM(B57:M57) -> 9353545.4
A58: Seminar for Fin. Sec | B58: 2233600 | D58: 150000 | I58: 630000 | M58: 3000 | N58: =SUM(B58:M58) -> 3016600
A59: Stationery | B59: 64000 | C59: 44100 | D59: 3100 | E59: 101000 | F59: 117100 | G59: 23250 | H59: 5000 | I59: 12000 | J59: 56800 | K59: 32800 | L59: 28700 | M59: 178100 | N59: =SUM(B59:M59) -> 665950
A60: Training | C60: 40000 | D60: 90000 | E60: 300000 | F60: 5155000 | H60: 1656100 | K60: 1105000 | N60: =SUM(B60:M60) -> 8346100
A61: Telephone | B61: 10000 | C61: 10000 | D61: 10000 | E61: 10000 | F61: 10000 | G61: 10000 | H61: 10000 | I61: 10000 | J61: 10000 | K61: 12000 | L61: 10000 | M61: 10000 | N61: =SUM(B61:M61) -> 122000
A62: History Book | J62: 2350000 | L62: 324000 | N62: =SUM(B62:M62) -> 2674000
A63: Transfer to colobus | D63: 40000000 | E63: 11000 | G63: 150000000 | N63: =SUM(B63:M63) -> 190011000
A64: Investment Trip | I64: 12240000 | N64: =SUM(B64:M64) -> 12240000
A65: UK Real est | B65: 18428000 | D65: 1215740 | E65: 50000 | F65: 9880000 | G65: 200000 | H65: 480000 | I65: 7850000 | N65: =SUM(B65:M65) -> 38103740
A66: Interview for tenders | F66: 1020000 | N66: =SUM(B66:M66) -> 1020000
A67: loan | J67: 2000000 | N67: =SUM(B67:M67) -> 2000000
A68: Christmas Bonus | M68: 454304 | N68: =SUM(B68:M68) -> 454304
A69: Uni Niger hostel | F69: 104898004 | H69: 40754973 | K69: 51540585 | L69: 1000000 | M69: 60823346 | N69: =SUM(B69:M69) -> 259016908
A70: Gifts | M70: 1800000 | N70: =SUM(B70:M70) -> 1800000
A71: Zenith Investment | E71: 100000000 | N71: =SUM(B71:M71) -> 100000000
A72: ECO bank | M72: 10000 | N72: =SUM(B72:M72) -> 10000
A73: Bank Charges | B73: 133746.61 | C73: 121014.15 | D73: 54941.34 | E73: 5747.2 | F73: 169589.33 | G73: 88866.71 | H73: 26266.2 | I73: 66618.17 | J73: 16343.18 | K73: 28947.06 | L73: 137221.41 | M73: 94487.11 | N73: =SUM(B73:M73) -> 943788.47
A74: BAL-Cash | B74: 101161 | C74: -98979 | D74: 90121 | E74: 72821 | F74: 820821 | G74: 716871 | H74: 162021 | I74: 561721 | J74: 567821 | K74: 273521 | L74: 570221 | M74: 198771 | N74: 198771
A75: FBN 1 | B75: 1.82938e+08 | C75: 1.0256161e+08 | D75: 83404793 | E75: 91931664 | F75: 4654336.1 | G75: 16632405 | H75: 42031948 | I75: 57059251 | J75: 81999240 | K75: 1.0193841e+08 | L75: 47686522 | M75: 1.749145e+08 | N75: 1.749145e+08
A76: FBN 2 | B76: 157873.31 | C76: -354340.06 | D76: 1991688.3 | E76: 1906160.5 | F76: 978760.83 | G76: 374042.73 | H76: 38295.6 | I76: 1261762.4 | J76: 2079392.6 | K76: 1301934.1 | L76: 682591.34 | M76: 3050987.4 | N76: 3050987.4
A77: Zenith Bank | B77: 1545213.4 | C77: 1545213.4 | D77: 2.0614974e+08 | E77: 4.7722924e+08 | F77: 3.7226786e+08 | G77: 2.2218288e+08 | H77: 1.839948e+08 | I77: 1.6251434e+08 | J77: 1.6363426e+08 | K77: 1.1206597e+08 | L77: 1.1734248e+08 | M77: 1.6391987e+08 | N77: 1.6391987e+08
B78: =SUM(B31:B77) -> 2.0736061e+08 | C78: =SUM(C31:C77) -> 2.1291998e+08 | D78: =SUM(D31:D77) -> 3.3648539e+08 | E78: =SUM(E31:E77) -> 6.7338739e+08 | F78: =SUM(F31:F77) -> 5.8585112e+08 | G78: =SUM(G31:G77) -> 3.9148248e+08 | H78: =SUM(H31:H77) -> 2.7088762e+08 | I78: =SUM(I31:I77) -> 3.3423111e+08 | ... N78: =SUM(N31:N77) -> 1.352516e+09

Sheet Fixed Asset
A1: NOTE 1: FIXED ASSETS
A2: DETAILS | B2: LAND & BUILDING FUND | C2: LAND/BUILDING ALUU HOSTEL | D2: BUILDING AWKA | E2: BUILDING UNI NIGER HOSTEL | F2: PLANT/EQUIP. FUND (10%) | G2: PLANT/EQUIP. ALUU HOSTEL (10%) | H2: MOTOR VEHICLE (25%) | I2: FURN/FITTINGS AWKA (10%) | J2: FURN/FITTINGS FUND (10%) | K2: FURN/FITTINGS ALUU HOSTEL (10%) | L2: TOTAL
B3: (N) | D3: (N) | F3: (N) | G3: (N) | H3: (N) | J3: (N) | K3: (N) | L3: (N)
A4: Cost/Valuation | B4: 460429049 | C4: 4.9074243e+08 | D4: 3.0343339e+08 | E4: = = | F4: 12852660 | G4: 14013695 | H4: 733450 | I4: 16493700 | J4: 14332867 | K4: 2370000 | L4: 1.2993971e+09
A5: Additions | B5: 450000 | D5: = = | E5: 259016908 | F5: 1721000 | G5: = = | H5: = = | I5: = = | J5: = = | K5: 19386100 | L5: =SUM(B5:K5) -> 280574008
A6: Disposal | B6: = = | C6: = = | D6: = = | E6: = = | F6: = = | G6: = = | H6: = = | I6: = = | J6: = = | K6: = = | L6: = =
A7: As at 31/03/2024 | B7: =SUM(B4:B5) -> 460879049 | C7: =SUM(C4:C5) -> 4.9074243e+08 | D7: =SUM(D4:D5) -> 3.0343339e+08 | E7: =SUM(E5:E5) -> 259016908 | F7: =SUM(F4:F5) -> 14573660 | G7: =SUM(G4:G5) -> 14013695 | H7: =SUM(H4:H5) -> 733450 | I7: =SUM(I4:I5) -> 16493700 | J7: =SUM(J4:J5) -> 14332867 | K7: =SUM(K4:K5) -> 21756100 | L7: =SUM(B7:K7) -> 1.5959752e+09
A8: Depriciation
A9: As at 1/1/2024 | B9: = = | C9: = = | D9: = = | E9: = = | F9: 5528458 | G9: 2802739 | H9: 485725 | I9: 1649370 | J9: 5573871.1 | K9: 474000 | L9: =SUM(B9:K9) -> 16514163
A10: Charge For the Year | B10: = = | C10: = = | D10: = = | E10: = = | F10: 1457366 | G10: 1401369.5 | H10: 183362.5 | I10: 1649370 | J10: 1433286.7 | K10: 237000 | L10: =SUM(B10:K10) -> 6361754.7
A11: As at 31/03/2024 | B11: = = | C11: = = | D11: = = | E11: = = | F11: =SUM(F9:F10) -> 6985824 | G11: =SUM(G9:G10) -> 4204108.5 | H11: =SUM(H9:H10) -> 669087.5 | I11: =SUM(I9:I10) -> 3298740 | J11: =SUM(J9:J10) -> 7007157.8 | K11: =SUM(K9:K10) -> 711000 | L11: =SUM(B11:K11) -> 22875918
A12: Netbook Value | B12: 460879049 | C12: 4.9074243e+08 | D12: 3.0343339e+08 | E12: 259016908 | F12: =F7-F11 -> 7587836 | G12: =G7-G11 -> 9809586.5 | H12: =H7-H11 -> 64362.5 | I12: =I7-I11 -> 13194960 | J12: =J7-J11 -> 7325709.2 | K12: =K7-K11 -> 21045100 | L12: =L7-L11 -> 1.5730993e+09

Sheet Trial Balance 
A1: SUPERANNUATION FUND OF THE NIGER ANAGLICAN CHURCHES
A2: Trial Balance as at 31th Dec 2024
A3: Details | C3: Dr | D3: Cr
C4: (N) | D4: (N)
A5: UK Investment | C5: 7885932390
A6: Nigeria Investments: Stock and Shares | C6: 38514209
A7: BGL | C7: 35784229
A8: Fidelity Bank | C8: 200000000
A9: ARM | C9: 100200000
A10: Globus | C10: 40000000
A11: Zenith Bank | C11: 100000000
A12: Loan to Joint Provinces | C12: 50000000
A13: Zenith Bank (London) | C13: 580286097
A14: Loan to Staff | C14: 1550000
A15: ICON Brokers | C15: 139
A16: Debtors | C16: 5503427
... A20: Suspense Account | C20: 34793671
A21: Bookshop House: Niger Diocese | D21: 44000
A22: Enugu Diocese | D22: 44000
A23: Niger Delta Diocese | D23: 17000
A24: Aba Diocese | D24: 27000
A25: Trinity College | D25: 40350
A26: PAYE | D26: 6864
A27: Contribution in Advance | D27: 31237933
A28: Loan From GARC | D28: 10000000
A29: Accumulated Fund | D29: 5.1723906e+09
A30: Contribution | D30: 4.2093374e+08
A31: Interest Income | D31: 87544266
A32: Dividend | D32: 901355.54
A33: Fin. Secs/Accountants Seminar Fee | D33: 2746000
A34: Pension Refund
A35: Card Replacement | D35: 30000
A36: Printing of Accounts/Sale of Scrab | D36: 265000
A37: ALUU Hostel rent | D37: 8392300
A38: Tender | D38: 1800000
A39: Awka Hostel Rent | D39: 4976700
A40: Zenith Doller Revaluation Gain | D40: 1738083
A41: UK Investment Revaluation Gain | D41: 9.364813e+09
A42: UK Investment Income | D42: 1.810721e+08
A43: UK Real Estate rent | D43: 50954981
A44: Uk Zenith Bank Interest | D44: 44549436
A45: UK Investment Mgt Fee | C45: 26561896
A46: UK Real Estate Charges | C46: 1447308.4
A47: Computer Software Upgrade | C47: 530000
A48: Audit fee | C48: 1000000
A49: Bad Debt | C49: 11597890
A50: Contingency | C50: 140500
A51: Car Insurance/Particulars Renewal | C51: 25700
A52: Car Running Cost | C52: 3442100
C53: =SUM(C5:C52) -> 1.2720935e+10 | D53: =SUM(D5:D52) -> 1.5384525e+10
C54: N | D54: N
C55: =C53 -> 1.2720935e+10 | D55: =D53 -> 1.5384525e+10
A56: Contribution Refund | C56: 29146859
A57: Exco Mgt. Committee Allowances | C57: 8535000
A58: Equipment - Fund | C58: 7587836
A59: Equipment - Aluu Hostel | C59: 9809586.5
A60: Furniture/Fittings - Fund | C60: 7325709.2
A61: Furniture/Fittings - Aluu Hostel | C61: 1659000
A62: GARC Expenses | C62: 2578950
A63: Furniture/Fittings - Awka Hostel | C63: 13194960
A64: Depreciation | C64: 6361754.7
A65: General Transport | C65: 190250
A66: Awka Hostel Dedication Expenses
A67: Hospitality to meetings | C67: 657200
A68: Foundation laying | C68: 580000
A69: Gifts | C69: 1800000
A70: Leave Allowance | C70: 418306.04
A71: Christmas Bonus | C71: 454304
A72: Lands - Fund | C72: 349862500
A73: Building - Secretariat/Staff Quarters | C73: 111016549
A74: Building- Awka | C74: 3.0343339e+08
A75: Land/Building - GARC
A76: Aluu Land CofO (Part Payment) | C76: 380000
A77: Aluu Hostel Expenses | C77: 290000
A78: Land and Building -Aluu Hostel | C78: 5.1012853e+08
A79: Land and Building -Uni Niger Hostel | C79: 259016908
A80: Motor Vehicle | C80: 64362.5
A81: Hazard Allowance
A82: Light/Power | C82: 462700
A83: Newspapers | C83: 14500
A84: Office Entertainment | C84: 213140
A85: Pensions Paid | C85: 3.1203929e+08
A86: Postage | C86: 135800
A87: Repairs | C87: 425500
A88: Staff Salaries/Allowances | C88: 9353545.4
A89: Interview for tenders | C89: 1020000
A90: Fin. Secs/Accountants Seminar Expenses | C90: 2386600
A91: Stationery | C91: 665950
A92: Staff and Exco Comm Trainning | C92: 8316100
A93: Telephone | C93: 122000
... A96: Cash/Bank Bal: FBN I | C96: 1.749145e+08
C97: =SUM(C55:C96) -> 1.4859478e+10 | D97: =SUM(D55:D96) -> 1.5384525e+10
C98: N | D98: N
C99: =C97 -> 1.4859478e+10 | D99: =D97 -> 1.5384525e+10
A100: FBN II | C100: 3050987.4
A101: CCB (in Liquidation) | C101: 73798.3
A102: FBN Dom I | C102: 801127
A103: FBN Dom II | C103: 92816
A104: Zenith Bank Dom (Ow) | C104: 3.4483648e+08
A105: Zenith Bank Dollar | C105: 822255.56
...

Sheet  Notes to the Account
D1: 2024 | E1: 2023
B2: NOTE 2: INVESTMENTS | C2: (N) | D2: (N) | E2: (N)
B3: UK Investment (Rathbones) | D3: 7885932390 | E3: 3.1781842e+09
B4: Stock (Nigeria) | D4: 38514209 | E4: 38514209
B5: BGL | D5: 35784229 | E5: 38257934
B6: Fidelity Bank | D6: 200000000 | E6: 200000000
B7: ARM | D7: 100200000 | E7: 100200000
B8: Stanbic/IBTC Investment | D8: 75272979 | E8: 51419900
B9: Globus Bank | D9: 40000000
B10: Zenith Bank (Nigeria) | D10: 100000000
B11: Zenith Bank (London) | D11: 5.802861e+08 | E11: 36174932
B12: UK Real Estate Investment | D12: 3.4951761e+09 | E12: 32851366
D13: =SUM(D3:D12) -> 1.2551166e+10 | E13: =SUM(E3:E12) -> 3.6756025e+09
B14: NOTE 2b: Stanbic/IBTC Investment | C14: $
B15: Opening Balance | C15: 161997.75 | D15: 51419900 | E15: 41324009
B16: Interest @ 1546 | C16: 15428.9 | D16: =C16*1546 -> 23853079 | E16: 10095891
B17: Closing Balance | C17: 177426.65 | D17: =SUM(D15:D16) -> 75272979 | E17: 51419900
A18: ; | B18: NOTE 2c: UK Real Estate Investment
B19: Opening Balance | D19: 32851366
B20: Investment Trips | D20: 63310740
B21: Purchase of Property | D21: 3.399014e+09
B22: Total | D22: =SUM(D19:D21) -> 3.4951761e+09
B23: NOTE 2d: BGL Investment
B24: Opening Balance | D24: 38257934 | E24: 50000000
B25: Refunded Sum | D25: 2473704.5 | E25: 11742066
B26: Closing Balance | D26: 35784229 | E26: 38257934
B28: NOTE 3: DEBTORS
B29: Ihiala | D29: 366177.5 | E29: 366177.5
B30: Niger West | D30: 5684.65 | E30: 5684.65
B31: Uyo | D31: 72857.88 | E31: 978089
B32: Niger Delta West | D32: 1449614.5 | E32: 490015.03
B33: Owerri | D33: 112.51
B34: Orlu | D34: 254671.68
B35: Isi Mbano | D35: 498235.01 | E35: 104181.41
B36: Ohaji/Egbema | D36: 11832.28
B37: Oru | D37: 16989.66 | E37: 16989.66
B38: Aba | D38: 59870.84 | E38: 54914.84
B39: Ukwa | D39: 190659.45
B40: Enugu | D40: 19800.47
B41: Nsukka | D41: 77088.61 | E41: 509903.74
B42: Oji River | D42: 2391778.2
B43: Enugu North | D43: 16205.73 | E43: 15184039
B44: Ngbo | D44: 20343.75 | E44: 20343.75
B45: Nike | D45: 51504.94
B46: Ogoni | E46: 294827
B47: Etche | E47: 436.19
B48: Egbu | E48: 328646.6
B49: Isiala Ngwa | E49: 360.461
D50: =SUM(D29:D45) -> 5503427.7 | E50: =SUM(E29:E49) -> 18354609
B51: NOTE 4: RECEIVABLES
B52: ICON Brokers | D52: 139 | E52: 139
B53: NOTE 5: CASH AND BANK BALANCES
B54: FBNI | D54: 1.749145e+08 | E54: 1.26986e+08
B55: FBN II | D55: 3050987.4 | E55: 237180.1
B56: CCB (in Liquidation) | D56: 73798.3
B57: FBN Dom I | D57: 801126.88 | E57: 801126.88
B58: FBN Dom II | D58: 92816 | E58: 92816
B59: Zenith Bank Pound (Ow) | D59: 3.4483648e+08 | E59: 708477.69
B60: Zenith Bank Dollar (Ow) | D60: 822255.56 | E60: 631347.48
B61: Zenith Bank (Naira) | D61: 1.6391987e+08 | E61: 1545213.4
B62: Access Bank Savings | D62: 70231.81 | E62: 70231.81
B63: ECO Bank | D63: 905335.91 | E63: 895385.91
B64: Globus Bank | D64: 10275341
B65: Cash in Hand | D65: 198771 | E65: 641997.55
D66: =SUM(D54:D65) -> 6.9996151e+08 | E66: =SUM(E54:E65) -> 1.3260977e+08
B67: NOTE 6: Account receivable
B68: Opening Balance | D68: 46391561 | E68: 57989451
B69: Bad debt (Written off) | D69: -11597890 | E69: -11597890
D70: =SUM(D68:D69) -> 34793671 | E70: 46391561
B71: NOTE 7: LIABILITIES
B72: Enugu Diocese | D72: 44000 | E72: 44000
B73: Niger Diocese | D73: 44000 | E73: 44000
B74: Niger Delta Diocese | D74: 17000 | E74: 17000
B75: Aba Diocese | D75: 27000 | E75: 27000
B76: Trinity College Umuahia | D76: 40350 | E76: 40350
B77: PAYE | D77: 6864 | E77: 6864
D78: =SUM(D72:D77) -> 179214 | E78: =SUM(E72:E77) -> 179214
B79: NOTE 8: CONTRIBUTION IN ADVANCE
B80: Niger | D80: 273 | E80: 966966.53
B81: Awka | D81: 971200.2 | E81: 864720.35
B82: Nnewi | D82: 128959.08 | E82: 129560.13
B83: Aguata | D83: 104.84 | E83: 75244.15
B84: Ogbaru | D84: 561722.99 | E84: 561722.99
B85: Niger East | D85: 195571.8 | E85: 195571.8
B86: Amichi | D86: 489316.84 | E86: 197812.69
B87: Niger Delta | D87: 5785.52 | E87: 5785.52
B88: Calabar | D88: 748124.48 | E88: 748124.48
B89: Niger Delta North | D89: 78773.96 | E89: 76963.17
B90: Okrika | D90: 30.25 | E90: 30.25
B91: Ahoada | D91: 194296.85 | E91: 23.3
B92: Ogoni | D92: 1705433
B93: Etche | D93: 758.98
B94: Northern Izon | D94: 749866.09 | E94: 1648647.5
B95: Ogbia | D95: 1066070.5 | E95: 1066070.5
B96: Evo | D96: 8779723.6 | E96: 8467897.7
B97: Mbaise | D97: 227639.95 | E97: 2586878
B98: Okigwe South | D98: 271908.21 | E98: 20000
B99: Egbu | D99: 1802850.9
B100: Ideato | D100: 1362797.3 | E100: 3760908.6
B101: On The Lake | D101: 3396264.2 | E101: 396264.17
...

Sheet Income Statement
A3: SUPERANNUATION ANGLICAN WORKERS EAST OF THE NIGER WELFARE FOUNDATION
A4: STATEMENT OF INCOME AND EXPENDITURE FOR THE PERIOD ENDED 31ST DECEMBER 2024
B6: NOTES | D6: (N)
A7: UK Investment Income | B7: 10 | D7: 1.810721e+08
A8: UK Real Estate Rent | D8: 50954981
A9: UK Zenith Bank Interest | D9: 44549436
A10: Nigerian Investment Income | B10: 11 | D10: =' Notes to the Account'!D181 -> 87544266
A11: Dividend | B11: 12 | D11: 901355.54
A12: Aluu Hostel Rent | D12: 8392300
A13: Awka Hostel Rent | D13: 4976700
A14: Other Income | B14: 13 | D14: 2095000
A15: Fin. Sec's Seminar | D15: 2746000
A16: Total Operating Income | D16: =SUM(D7:D15) -> 3.8323214e+08
A17: Other Operating Expenses | B17: 14 | D17: -66653040
A18: Personnel Cost | B18: 15 | D18: -10226155
A19: Depreciation | B19: 1 | D19: -6361754.7
A20: Finance Cost | D20: -29316674
A21: Bad Debt | B21: 6 | D21: -11597890
A22: Surplus For the Year | D22: =SUM(D16:D21) -> 2.5907662e+08

Sheet Final Account
A1: SUPERANNUATION ANGLICAN WORKERS EAST OF THE NIGER WELFARE FOUNDATION
A2: STATEMENT OF FINANCIAL POSITION AS AT 31ST DECEMBER 2024
C4: ALUU | D4: AWKA | E4: FUND | F4: 2024 | G4: 2023
B5: Notes | C5: (N) | D5: (N) | E5: (N) | F5: (N) | G5: (N)
A6: Non Current Assets | B6: 1 | C6: 5.2159711e+08 | D6: 3.1662835e+08 | E6: 7.3487386e+08 | F6: =SUM(C6:E6) -> 1.5730993e+09 | G6: 1.2988871e+09
A7: Investments | B7: 2 | C7: = = | D7: = = | E7: =' Notes to the Account'!D13 -> 1.2551166e+10 | F7: =' Notes to the Account'!D13 -> 1.2551166e+10 | G7: 3.6394276e+09
A8: Debtors | B8: 3 | C8: = = | D8: = = | E8: 5503427 | F8: =SUM(C8:E8) -> 5503427 | G8: 18354609
A9: Computer Software | C9: = = | D9: = = | E9: 530000 | F9: =SUM(C9:E9) -> 530000 | G9: 530000
A10: Receivables | B10: 4 | C10: = = | D10: = = | E10: 139 | F10: =SUM(C10:E10) -> 139 | G10: 139
A11: Bank and Cash Balances | B11: 5 | C11: = = | D11: = = | E11: =' Notes to the Account'!D66 -> 6.9996151e+08 | F11: =SUM(C11:E11) -> 6.9996151e+08 | G11: 1.688585e+08
A12: Loan to Joint Province | C12: = = | D12: = = | E12: 50000000 | F12: =SUM(C12:E12) -> 50000000 | G12: 50000000
A13: Loan to Staff | C13: = = | D13: = = | E13: 1550000 | F13: =SUM(C13:E13) -> 1550000 | G13: 510000
A14: Recoverable GARC Expenses | C14: = = | D14: = = | E14: 2578950 | F14: =SUM(C14:E14) -> 2578950 | G14: 1948950
A15: Account Receivable | B15: 6 | C15: = = | D15: = = | E15: =' Notes to the Account'!D70 -> 34793671 | F15: =E15 -> 34793671 | G15: 46391561
A16: Total Assets | C16: =SUM(C6:C15) -> 5.2159711e+08 | D16: =SUM(D6:D15) -> 3.1662835e+08 | E16: =SUM(E6:E15) -> 1.4080958e+10 | F16: =SUM(F6:F15) -> 1.4919183e+10 | G16: =SUM(G6:G15) -> 5.2249084e+09
A17: Liabilities | B17: 7 | C17: = = | D17: = = | E17: -179214 | F17: -179214 | G17: -1179214
A18: Loan from GARC | C18: = = | D18: = = | E18: -10000000 | F18: -10000000 | G18: -10000000
A19: Contribution in Advance | B19: 8 | C19: = = | D19: = = | E19: -31237660 | F19: =E19 -> -31237660 | G19: -41338632
A20: Net Total Assets | C20: =SUM(C16:C19) -> 5.2159711e+08 | D20: =SUM(D16:D19) -> 3.1662835e+08 | E20: =SUM(E16:E19) -> 1.4039541e+10 | F20: =SUM(C20:E20) -> 1.4877766e+10 | G20: =SUM(G16:G19) -> 5.1723906e+09
A21: Accumulated Fund | B21: 9 | C21: = = | D21: = = | E21: = = | F21: 14877766153 | G21: =' Notes to the Account'!E143 -> 5.1723906e+09
